MANIFEST.in
README.md
setup.cfg
setup.py
peigen/__init__.py
peigen.egg-info/PKG-INFO
peigen.egg-info/SOURCES.txt
peigen.egg-info/dependency_links.txt
peigen.egg-info/not-zip-safe
peigen.egg-info/top_level.txt
peigen/include/Eigen/CMakeLists.txt
peigen/include/Eigen/Cholesky
peigen/include/Eigen/CholmodSupport
peigen/include/Eigen/Core
peigen/include/Eigen/Dense
peigen/include/Eigen/Eigen
peigen/include/Eigen/Eigenvalues
peigen/include/Eigen/Geometry
peigen/include/Eigen/Householder
peigen/include/Eigen/IterativeLinearSolvers
peigen/include/Eigen/Jacobi
peigen/include/Eigen/LU
peigen/include/Eigen/MetisSupport
peigen/include/Eigen/OrderingMethods
peigen/include/Eigen/PaStiXSupport
peigen/include/Eigen/PardisoSupport
peigen/include/Eigen/QR
peigen/include/Eigen/QtAlignedMalloc
peigen/include/Eigen/SPQRSupport
peigen/include/Eigen/SVD
peigen/include/Eigen/Sparse
peigen/include/Eigen/SparseCholesky
peigen/include/Eigen/SparseCore
peigen/include/Eigen/SparseLU
peigen/include/Eigen/SparseQR
peigen/include/Eigen/StdDeque
peigen/include/Eigen/StdList
peigen/include/Eigen/StdVector
peigen/include/Eigen/SuperLUSupport
peigen/include/Eigen/UmfPackSupport
peigen/include/Eigen/src/Cholesky/LDLT.h
peigen/include/Eigen/src/Cholesky/LLT.h
peigen/include/Eigen/src/Cholesky/LLT_LAPACKE.h
peigen/include/Eigen/src/CholmodSupport/CholmodSupport.h
peigen/include/Eigen/src/Core/Array.h
peigen/include/Eigen/src/Core/ArrayBase.h
peigen/include/Eigen/src/Core/ArrayWrapper.h
peigen/include/Eigen/src/Core/Assign.h
peigen/include/Eigen/src/Core/AssignEvaluator.h
peigen/include/Eigen/src/Core/Assign_MKL.h
peigen/include/Eigen/src/Core/BandMatrix.h
peigen/include/Eigen/src/Core/Block.h
peigen/include/Eigen/src/Core/BooleanRedux.h
peigen/include/Eigen/src/Core/CommaInitializer.h
peigen/include/Eigen/src/Core/ConditionEstimator.h
peigen/include/Eigen/src/Core/CoreEvaluators.h
peigen/include/Eigen/src/Core/CoreIterators.h
peigen/include/Eigen/src/Core/CwiseBinaryOp.h
peigen/include/Eigen/src/Core/CwiseNullaryOp.h
peigen/include/Eigen/src/Core/CwiseTernaryOp.h
peigen/include/Eigen/src/Core/CwiseUnaryOp.h
