Metadata-Version: 1.0
Name: peigen
Version: 0.0.9
Summary: Python wrapper for Eigen C++ header
Home-page: https://github.com/fred3m/peigen
Author: Fred Moolekamp
Author-email: fred.moolekamp@gmail.com
License: UNKNOWN
Keywords: eigen,numerical
Platform: UNKNOWN
